README.rst
setup.cfg
setup.py
stoneFilters.egg-info/PKG-INFO
stoneFilters.egg-info/SOURCES.txt
stoneFilters.egg-info/dependency_links.txt
stoneFilters.egg-info/requires.txt
stoneFilters.egg-info/top_level.txt
stonefilters/__init__.py
stonefilters/models.py
stonefilters/settings.py
stonefilters/stonefilters.py
stonefilters/urls.py
stonefilters/wsgi.py
stonefilters/migrations/0001_initial.py
stonefilters/migrations/0002_auto_20170111_1644.py
stonefilters/migrations/__init__.py