Metadata-Version: 1.0
Name: stoneFilters
Version: 0.1.0
Summary: UNKNOWN
Home-page: http://www.stoneworksolutions.net
Author: Antonio Palomo Cardenas
Author-email: antonio.palomo@stoneworksolutions.net
License: UNKNOWN
Platform: UNKNOWN
